LICENSE
README.md
setup.py
SunshineLib/EmailVer.py
SunshineLib/__init__.py
SunshineLib/copr.py
SunshineLib.egg-info/PKG-INFO
SunshineLib.egg-info/SOURCES.txt
SunshineLib.egg-info/dependency_links.txt
SunshineLib.egg-info/top_level.txt