Metadata-Version: 2.1
Name: SunshineLib
Version: 0.0.4
Summary: 此库为阳光工作室专属库。
Home-page: https://github.com/
Author: Haoyang Zhang
Author-email: yangguang_gongzuo@qq.com
License: UNKNOWN
Platform: UNKNOWN
Classifier: Programming Language :: Python :: 3
Classifier: License :: OSI Approved :: MIT License
Classifier: Operating System :: OS Independent
License-File: LICENSE
